{"UCLA":{"lat":34.068921,"lng":-118.4451811,"state":"California"},"Columbia University":{"lat":40.8075355,"lng":-73.9625727,"state":"New York"},"Jacobi":{"lat":40.8560285,"lng":-73.8463633,"state":"New York"},"Center for Rheumatology, LLP":{"lat":42.6860238,"lng":-73.8425874,"state":"New York"},"University of Alabama":{"lat":33.2140233,"lng":-87.5391418,"state":"Alabama"},"Winthrop":{"lat":34.939393,"lng":-81.0321286,"state":"South Carolina"},"University of Kentucky":{"lat":38.0306511,"lng":-84.5039697,"state":"Kentucky"},"Northwell":{"lat":40.8101231,"lng":-73.1893279,"state":"New York"},"Dartmouth-Hitchcock Medical Center":{"lat":43.67536399999999,"lng":-72.2729872,"state":"New Hampshire"},"University of Pittsburgh":{"lat":40.4415442,"lng":-79.9593563,"state":"Pennsylvania"},"Center for Rheum & Bone Research":{"lat":43.086968,"lng":-73.807079,"state":"New York"},"Hospital for Special Surgery":{"lat":40.7649401,"lng":-73.9529503,"state":"New York"},"Mount Sinai":{"lat":40.6187324,"lng":-73.9429871,"state":"New York"},"Southwest Florida":{"lat":26.5337051,"lng":-81.7553083,"state":"Florida"},"MGH":{"lat":42.3613671,"lng":-71.0681857,"state":"Massachusetts"},"Cleveland Clinic":{"lat":41.502653,"lng":-81.62098,"state":"Ohio"},"Oregon Health & Science University":{"lat":45.4989098,"lng":-122.6858606,"state":"Oregon"},"Brigham and Women's Hospital":{"lat":42.3362325,"lng":-71.1065443,"state":"Massachusetts"},"Washington University St. Louis":{"lat":38.6487895,"lng":-90.31079620000001,"state":"Missouri"},"SUNY Downstate":{"lat":40.6552459,"lng":-73.945734,"state":"New York"},"UMichigan":{"lat":42.2780436,"lng":-83.7382241,"state":"Michigan"},"UT Houston":{"lat":29.7034179,"lng":-95.4030452,"state":"Texas"},"Robert W. Levin, MD, PA":{"lat":27.9885277,"lng":-82.7455902,"state":"Florida"},"NYU":{"lat":40.72951339999999,"lng":-73.9964609,"state":"New York"},"Seattle Rheumatology":{"lat":47.70457340000001,"lng":-122.3324113,"state":"Washington"},"Brigid Freyne MD, Inc.":{"lat":33.555874,"lng":-117.163786,"state":"California"},"Sarasota Arthritis Research Center":{"lat":27.3007467,"lng":-82.5320475,"state":"Florida"},"Southern Ohio Rheumatology, Inc.":{"lat":38.7293812,"lng":-82.8577636,"state":"Ohio"},"UNC Med":{"lat":35.906058,"lng":-79.052199,"state":"North Carolina"},"UCSF":{"lat":37.7627655,"lng":-122.457753,"state":"California"},"Northwestern":{"lat":42.0564594,"lng":-87.67526699999999,"state":"Illinois"},"Nazanin Firooz MD, Inc. West Hills, CA":{"lat":34.2014202,"lng":-118.6297387,"state":"California"},"Altoona Research Center":{"lat":40.4359798,"lng":-78.4176739,"state":"Pennsylvania"},"Metroplex Clinical Research Center":{"lat":32.880948,"lng":-96.76601199999999,"state":"Texas"},"UPenn":{"lat":39.9522188,"lng":-75.1932137,"state":"Pennsylvania"},"U Wisconsin":{"lat":43.076592,"lng":-89.4124875,"state":"Wisconsin"},"Baylor":{"lat":31.5497007,"lng":-97.1143046,"state":"Texas"},"UVA":{"lat":38.0335529,"lng":-78.5079772,"state":"Virginia"},"Mt. Sinai Hospital, Canada":{"lat":43.6574634,"lng":-79.3903693,"state":"Ontario"},"Liam Martin":{"lat":42.3466764,"lng":-71.0972178,"state":"Massachusetts"},"Sibel Aydin, Ottawa":{"lat":45.4215296,"lng":-75.69719309999999,"state":"Ontario"},"Houston":{"lat":29.7604267,"lng":-95.3698028,"state":"Texas"},"Atlanta":{"lat":33.7489954,"lng":-84.3879824,"state":"Georgia"},"Norfolk":{"lat":36.8507689,"lng":-76.28587259999999,"state":"Virginia"},"Lebanon":{"lat":33.854721,"lng":35.862285,"state":""},"Philadelphia":{"lat":39.9525839,"lng":-75.1652215,"state":"Pennsylvania"},"Pittsburgh":{"lat":40.44062479999999,"lng":-79.9958864,"state":"Pennsylvania"},"New Castle County":{"lat":39.5392979,"lng":-75.667356,"state":"Delaware"},"New Hyde Park":{"lat":40.7351018,"lng":-73.6879082,"state":"New York"},"New York":{"lat":40.7127753,"lng":-74.0059728,"state":"New York"},"Hartford":{"lat":36.097897,"lng":-95.8526426,"state":"Oklahoma"},"Shreveport":{"lat":32.5251516,"lng":-93.7501789,"state":"Louisiana"},"Palo Alto":{"lat":37.4418834,"lng":-122.1430195,"state":"California"},"Chicago":{"lat":41.8781136,"lng":-87.6297982,"state":"Illinois"},"Marshfield":{"lat":44.6688524,"lng":-90.1717987,"state":"Wisconsin"},"Boston":{"lat":42.3600825,"lng":-71.0588801,"state":"Massachusetts"},"Nashville":{"lat":36.1626638,"lng":-86.7816016,"state":"Tennessee"},"Charleston":{"lat":32.7764749,"lng":-79.93105120000001,"state":"South Carolina"},"Evanston":{"lat":42.0450722,"lng":-87.68769689999999,"state":"Illinois"},"Portland":{"lat":45.5154586,"lng":-122.6793461,"state":"Oregon"},"Salt Lake City":{"lat":40.7607793,"lng":-111.8910474,"state":"Utah"},"San Diego":{"lat":32.715738,"lng":-117.1610838,"state":"California"},"Indianapolis":{"lat":39.768403,"lng":-86.158068,"state":"Indiana"},"Seattle":{"lat":47.6062095,"lng":-122.3320708,"state":"Washington"},"St. Louis":{"lat":38.6270025,"lng":-90.19940419999999,"state":"Missouri"},"Kansas City":{"lat":39.0997265,"lng":-94.5785667,"state":"Missouri"},"San Francisco":{"lat":37.7749295,"lng":-122.4194155,"state":"California"},"Minneapolis":{"lat":44.977753,"lng":-93.2650108,"state":"Minnesota"},"Worcester":{"lat":42.2625932,"lng":-71.8022934,"state":"Massachusetts"},"Albuquerque":{"lat":35.0843859,"lng":-106.650422,"state":"New Mexico"}}